{
    "key": "group_64e3d1dd625a1",
    "title": "Block: Timeline",
    "fields": [
        {
            "key": "field_6508ad929efc7",
            "label": "Block: Timeline",
            "name": "",
            "aria-label": "",
            "type": "message",
            "instructions": "",
            "required": 0,
            "conditional_logic": 0,
            "wrapper": {
                "width": "",
                "class": "",
                "id": ""
            },
            "message": "",
            "new_lines": "wpautop",
            "esc_html": 0
        },
        {
            "key": "field_64e3d296acc85",
            "label": "Headline",
            "name": "headline",
            "aria-label": "",
            "type": "text",
            "instructions": "",
            "required": 0,
            "conditional_logic": 0,
            "wrapper": {
                "width": "",
                "class": "",
                "id": ""
            },
            "default_value": "",
            "maxlength": "",
            "placeholder": "",
            "prepend": "",
            "append": ""
        },
        {
            "key": "field_64e3d24263961",
            "label": "Background",
            "name": "background",
            "aria-label": "",
            "type": "true_false",
            "instructions": "",
            "required": 0,
            "conditional_logic": 0,
            "wrapper": {
                "width": "",
                "class": "",
                "id": ""
            },
            "message": "",
            "default_value": 0,
            "ui_on_text": "Off-White",
            "ui_off_text": "White",
            "ui": 1
        },
        {
            "key": "field_64e3d1de2906c",
            "label": "Shortcode",
            "name": "shortcode",
            "aria-label": "",
            "type": "text",
            "instructions": "Enter the shortcode from Timeline > Shortcodes builder",
            "required": 0,
            "conditional_logic": 0,
            "wrapper": {
                "width": "",
                "class": "",
                "id": ""
            },
            "default_value": "",
            "maxlength": "",
            "placeholder": "",
            "prepend": "",
            "append": ""
        }
    ],
    "location": [
        [
            {
                "param": "block",
                "operator": "==",
                "value": "acf\/timeline"
            }
        ]
    ],
    "menu_order": 0,
    "position": "normal",
    "style": "default",
    "label_placement": "top",
    "instruction_placement": "label",
    "hide_on_screen": "",
    "active": true,
    "description": "",
    "show_in_rest": 0,
    "modified": 1697142985
}
